CODE_OF_CONDUCT.md
LICENSE
MANIFEST.in
README.md
SECURITY.md
requirements.txt
setup.cfg
setup.py
jetson_stats.egg-info/PKG-INFO
jetson_stats.egg-info/SOURCES.txt
jetson_stats.egg-info/dependency_links.txt
jetson_stats.egg-info/entry_points.txt
jetson_stats.egg-info/not-zip-safe
jetson_stats.egg-info/requires.txt
jetson_stats.egg-info/top_level.txt
jtop/__init__.py
jtop/__main__.py
jtop/github.py
jtop/jetson_config.py
jtop/jetson_release.py
jtop/jtop.py
jtop/service.py
jtop/terminal_colors.py
jtop/core/__init__.py
jtop/core/command.py
jtop/core/common.py
jtop/core/config.py
jtop/core/cpu.py
jtop/core/engine.py
jtop/core/exceptions.py
jtop/core/fan.py
jtop/core/jetson_clocks.py
jtop/core/jetson_libraries.py
jtop/core/jetson_variables.py
jtop/core/memory.py
jtop/core/nvpmodel.py
jtop/core/swap.py
jtop/core/tegra_parse.py
jtop/core/tegrastats.py
jtop/gui/__init__.py
jtop/gui/jtopgui.py
jtop/gui/jtopguiconfig.py
jtop/gui/jtopguimenu.py
jtop/gui/pall.py
jtop/gui/pcontrol.py
jtop/gui/pcpu.py
jtop/gui/pengine.py
jtop/gui/pgpu.py
jtop/gui/pinfo.py
jtop/gui/pmem.py
jtop/gui/lib/__init__.py
jtop/gui/lib/button.py
jtop/gui/lib/chart.py
jtop/gui/lib/common.py
jtop/gui/lib/linear_gauge.py
scripts/jetson_swap
scripts/jtop_env.sh
services/jtop.service