Metadata-Version: 2.1
Name: jetson-stats
Version: 4.1.5
Summary: Interactive system-monitor and process viewer for all NVIDIA Jetson [Orin, Xavier, Nano, TX] series
Home-page: https://rnext.it/jetson_stats
Author: Raffaello Bonghi
Author-email: raffaello@rnext.it
License: AGPL-3.0
Project-URL: Documentation, https://rnext.it/jetson_stats
Project-URL: Funding, https://github.com/sponsors/rbonghi
Project-URL: Say Thanks!, https://discord.gg/BFbuJNhYzS
Project-URL: Source, https://github.com/rbonghi/jetson_stats
Project-URL: Tracker, https://github.com/rbonghi/jetson_stats/issues
Project-URL: Examples, https://github.com/rbonghi/jetson_stats/tree/master/examples
Keywords: jetson_stats jtop python system-monitor docker                nvidia Jetson Orin AGXOrin Xavier AGXXavier XavierNX Nano TX1 TX2 process viewer
Platform: linux
Platform: linux2
Platform: darwin
Classifier: Development Status :: 5 - Production/Stable
Classifier: Intended Audience :: Developers
Classifier: Topic :: Software Development :: Embedded Systems
Classifier: Topic :: Software Development :: Debuggers
Classifier: Topic :: Software Development :: Libraries
Classifier: Topic :: Software Development :: User Interfaces
Classifier: Topic :: System :: Hardware
Classifier: Topic :: System :: Logging
Classifier: Topic :: System :: Monitoring
Classifier: Topic :: System :: Operating System
Classifier: Topic :: System :: Operating System Kernels
Classifier: Topic :: System :: Shells
Classifier: Topic :: System :: Systems Administration
Classifier: Topic :: Terminals
Classifier: License :: OSI Approved :: GNU Affero General Public License v3 or later (AGPLv3+)
Classifier: Programming Language :: Unix Shell
Classifier: Programming Language :: Python :: 2
Classifier: Programming Language :: Python :: 2.7
Classifier: Programming Language :: Python :: 3
Classifier: Programming Language :: Python :: 3.6
Classifier: Programming Language :: Python :: 3.8
Classifier: Programming Language :: Python :: 3.9
Classifier: Programming Language :: Python :: 3.10
Classifier: Programming Language :: Python :: 3.11
Classifier: Operating System :: POSIX :: Linux
Requires-Python: >=2.7, !=3.0.*, !=3.1.*, !=3.2.*, !=3.3.*, <4
License-File: LICENSE
